{
  "generatedAt": "2026-05-07T12:27:18.253Z",
  "files": {
    "events.json": "2026-05-07T12:27:18.209Z",
    "whats-new.json": "2026-05-07T12:27:17.079Z",
    "crawfish-prices.json": "2026-05-07T12:27:07.627Z",
    "crawfish-season.json": "2026-05-07T12:27:07.630Z",
    "live-music.json": "2026-05-07T12:26:49.831Z",
    "kids-eat-free.json": null,
    "weekend-brunch.json": null,
    "whos-got-it.json": "2026-05-07T12:26:49.861Z",
    "community-recs.json": "2026-05-07T12:26:49.826Z",
    "cajun-connection.json": "2026-05-07T12:26:49.825Z"
  }
}
